{"hierarchy":{"paths":[[]]},"identifier":{"interfaceLanguage":"swift","url":"doc:\/\/SwiftMarkdownView\/documentation\/SwiftMarkdownView"},"topicSections":[{"title":"はじめに","identifiers":["doc:\/\/SwiftMarkdownView\/documentation\/SwiftMarkdownView\/MarkdownView","doc:\/\/SwiftMarkdownView\/documentation\/SwiftMarkdownView\/MarkdownContent","doc:\/\/SwiftMarkdownView\/documentation\/SwiftMarkdownView\/GettingStarted"],"anchor":"はじめに"},{"title":"シンタックスハイライト","identifiers":["doc:\/\/SwiftMarkdownView\/documentation\/SwiftMarkdownView\/SyntaxHighlighter","doc:\/\/SwiftMarkdownView\/documentation\/SwiftMarkdownView\/PlainTextHighlighter","doc:\/\/SwiftMarkdownView\/documentation\/SwiftMarkdownView\/HighlightState","doc:\/\/SwiftMarkdownView\/documentation\/SwiftMarkdownView\/HighlightedCodeView","doc:\/\/SwiftMarkdownView\/documentation\/SwiftMarkdownView\/SyntaxHighlighting"],"anchor":"シンタックスハイライト"},{"title":"Aside（コールアウト）","identifiers":["doc:\/\/SwiftMarkdownView\/documentation\/SwiftMarkdownView\/DefaultAsideStyle","doc:\/\/SwiftMarkdownView\/documentation\/SwiftMarkdownView\/Asides"],"anchor":"Asideコールアウト"},{"title":"Mermaidダイアグラム","identifiers":["doc:\/\/SwiftMarkdownView\/documentation\/SwiftMarkdownView\/MermaidDiagrams"],"anchor":"Mermaidダイアグラム"},{"title":"ドメインモデル","identifiers":["doc:\/\/SwiftMarkdownView\/documentation\/SwiftMarkdownView\/MarkdownBlock","doc:\/\/SwiftMarkdownView\/documentation\/SwiftMarkdownView\/MarkdownInline","doc:\/\/SwiftMarkdownView\/documentation\/SwiftMarkdownView\/AsideKind","doc:\/\/SwiftMarkdownView\/documentation\/SwiftMarkdownView\/TableData","doc:\/\/SwiftMarkdownView\/documentation\/SwiftMarkdownView\/ListItem"],"anchor":"ドメインモデル"},{"title":"スタイル","identifiers":["doc:\/\/SwiftMarkdownView\/documentation\/SwiftMarkdownView\/LinkStyle","doc:\/\/SwiftMarkdownView\/documentation\/SwiftMarkdownView\/CodeBlockStyle","doc:\/\/SwiftMarkdownView\/documentation\/SwiftMarkdownView\/TableStyle","doc:\/\/SwiftMarkdownView\/documentation\/SwiftMarkdownView\/AsideStyle"],"anchor":"スタイル"},{"title":"Mermaid","abstract":[{"type":"strong","inlineContent":[{"type":"text","text":"SwiftMarkdownViewHighlightJS"}]},{"type":"text","text":": HighlightJSによる50+言語対応シンタックスハイライト"}],"identifiers":["doc:\/\/SwiftMarkdownView\/documentation\/SwiftMarkdownView\/MermaidDiagramView","doc:\/\/SwiftMarkdownView\/documentation\/SwiftMarkdownView\/AdaptiveMermaidView","doc:\/\/SwiftMarkdownView\/documentation\/SwiftMarkdownView\/MermaidFallbackView"],"anchor":"Mermaid"},{"title":"Protocols","generated":true,"identifiers":["doc:\/\/SwiftMarkdownView\/documentation\/SwiftMarkdownView\/HeadingStyle","doc:\/\/SwiftMarkdownView\/documentation\/SwiftMarkdownView\/MermaidScriptProvider"],"anchor":"Protocols"},{"title":"Structures","generated":true,"identifiers":["doc:\/\/SwiftMarkdownView\/documentation\/SwiftMarkdownView\/AsideCatalogView","doc:\/\/SwiftMarkdownView\/documentation\/SwiftMarkdownView\/AsideStyleCatalogView","doc:\/\/SwiftMarkdownView\/documentation\/SwiftMarkdownView\/BoldLinkStyle","doc:\/\/SwiftMarkdownView\/documentation\/SwiftMarkdownView\/BorderlessTableStyle","doc:\/\/SwiftMarkdownView\/documentation\/SwiftMarkdownView\/BundledMermaidScriptProvider","doc:\/\/SwiftMarkdownView\/documentation\/SwiftMarkdownView\/CDNMermaidScriptProvider","doc:\/\/SwiftMarkdownView\/documentation\/SwiftMarkdownView\/CardTableStyle","doc:\/\/SwiftMarkdownView\/documentation\/SwiftMarkdownView\/CatalogSectionCard","doc:\/\/SwiftMarkdownView\/documentation\/SwiftMarkdownView\/CategoryItemRow","doc:\/\/SwiftMarkdownView\/documentation\/SwiftMarkdownView\/ClassicLinkStyle","doc:\/\/SwiftMarkdownView\/documentation\/SwiftMarkdownView\/CodeBlockCatalogView","doc:\/\/SwiftMarkdownView\/documentation\/SwiftMarkdownView\/CodeBlockStyleCatalogView","doc:\/\/SwiftMarkdownView\/documentation\/SwiftMarkdownView\/CodeSnippetView","doc:\/\/SwiftMarkdownView\/documentation\/SwiftMarkdownView\/ColoredHeadingStyle","doc:\/\/SwiftMarkdownView\/documentation\/SwiftMarkdownView\/CompactHeadingStyle","doc:\/\/SwiftMarkdownView\/documentation\/SwiftMarkdownView\/DefaultCodeBlockStyle","doc:\/\/SwiftMarkdownView\/documentation\/SwiftMarkdownView\/DefaultHeadingStyle","doc:\/\/SwiftMarkdownView\/documentation\/SwiftMarkdownView\/DefaultLinkStyle","doc:\/\/SwiftMarkdownView\/documentation\/SwiftMarkdownView\/DefaultTableStyle","doc:\/\/SwiftMarkdownView\/documentation\/SwiftMarkdownView\/DividedHeadingStyle","doc:\/\/SwiftMarkdownView\/documentation\/SwiftMarkdownView\/HeadingCatalogView","doc:\/\/SwiftMarkdownView\/documentation\/SwiftMarkdownView\/HeadingStyleCatalogView","doc:\/\/SwiftMarkdownView\/documentation\/SwiftMarkdownView\/ImageCatalogView","doc:\/\/SwiftMarkdownView\/documentation\/SwiftMarkdownView\/InlineCodeCatalogView","doc:\/\/SwiftMarkdownView\/documentation\/SwiftMarkdownView\/LinkCatalogView","doc:\/\/SwiftMarkdownView\/documentation\/SwiftMarkdownView\/LinkStyleCatalogView","doc:\/\/SwiftMarkdownView\/documentation\/SwiftMarkdownView\/MarkdownCatalogItem","doc:\/\/SwiftMarkdownView\/documentation\/SwiftMarkdownView\/MarkdownCatalogListView","doc:\/\/SwiftMarkdownView\/documentation\/SwiftMarkdownView\/MarkdownCatalogSplitView","doc:\/\/SwiftMarkdownView\/documentation\/SwiftMarkdownView\/MarkdownCatalogView","doc:\/\/SwiftMarkdownView\/documentation\/SwiftMarkdownView\/MarkdownPlaygroundView","doc:\/\/SwiftMarkdownView\/documentation\/SwiftMarkdownView\/MarkdownPreviewCard","doc:\/\/SwiftMarkdownView\/documentation\/SwiftMarkdownView\/MarkdownRenderingOptions","doc:\/\/SwiftMarkdownView\/documentation\/SwiftMarkdownView\/MermaidCatalogView","doc:\/\/SwiftMarkdownView\/documentation\/SwiftMarkdownView\/MinimalCodeBlockStyle","doc:\/\/SwiftMarkdownView\/documentation\/SwiftMarkdownView\/MonochromeLinkStyle","doc:\/\/SwiftMarkdownView\/documentation\/SwiftMarkdownView\/OrderedListCatalogView","doc:\/\/SwiftMarkdownView\/documentation\/SwiftMarkdownView\/ParagraphCatalogView","doc:\/\/SwiftMarkdownView\/documentation\/SwiftMarkdownView\/RenderingOptionsCatalogView","doc:\/\/SwiftMarkdownView\/documentation\/SwiftMarkdownView\/SoftBreakCatalogView","doc:\/\/SwiftMarkdownView\/documentation\/SwiftMarkdownView\/StripedTableStyle","doc:\/\/SwiftMarkdownView\/documentation\/SwiftMarkdownView\/SubtleLinkStyle","doc:\/\/SwiftMarkdownView\/documentation\/SwiftMarkdownView\/SyntaxHighlighterCatalogView","doc:\/\/SwiftMarkdownView\/documentation\/SwiftMarkdownView\/TableCatalogView","doc:\/\/SwiftMarkdownView\/documentation\/SwiftMarkdownView\/TableRow","doc:\/\/SwiftMarkdownView\/documentation\/SwiftMarkdownView\/TableStyleCatalogView","doc:\/\/SwiftMarkdownView\/documentation\/SwiftMarkdownView\/TaskListCatalogView","doc:\/\/SwiftMarkdownView\/documentation\/SwiftMarkdownView\/TerminalCodeBlockStyle","doc:\/\/SwiftMarkdownView\/documentation\/SwiftMarkdownView\/TextStylesCatalogView","doc:\/\/SwiftMarkdownView\/documentation\/SwiftMarkdownView\/ThematicBreakCatalogView","doc:\/\/SwiftMarkdownView\/documentation\/SwiftMarkdownView\/UnorderedListCatalogView"],"anchor":"Structures"},{"title":"Variables","generated":true,"identifiers":["doc:\/\/SwiftMarkdownView\/documentation\/SwiftMarkdownView\/defaultMermaidScriptProvider"],"anchor":"Variables"},{"title":"Enumerations","generated":true,"identifiers":["doc:\/\/SwiftMarkdownView\/documentation\/SwiftMarkdownView\/BlockElementItem","doc:\/\/SwiftMarkdownView\/documentation\/SwiftMarkdownView\/ConfigurationItem","doc:\/\/SwiftMarkdownView\/documentation\/SwiftMarkdownView\/DesignSystemItem","doc:\/\/SwiftMarkdownView\/documentation\/SwiftMarkdownView\/InlineElementItem","doc:\/\/SwiftMarkdownView\/documentation\/SwiftMarkdownView\/MarkdownCatalogCategory","doc:\/\/SwiftMarkdownView\/documentation\/SwiftMarkdownView\/MarkdownCatalogRouter","doc:\/\/SwiftMarkdownView\/documentation\/SwiftMarkdownView\/MarkdownColors","doc:\/\/SwiftMarkdownView\/documentation\/SwiftMarkdownView\/MarkdownRadius","doc:\/\/SwiftMarkdownView\/documentation\/SwiftMarkdownView\/MarkdownSpacing","doc:\/\/SwiftMarkdownView\/documentation\/SwiftMarkdownView\/MarkdownTypographyMapping","doc:\/\/SwiftMarkdownView\/documentation\/SwiftMarkdownView\/MermaidScriptSource","doc:\/\/SwiftMarkdownView\/documentation\/SwiftMarkdownView\/TableAlignment"],"anchor":"Enumerations"},{"title":"Extended Modules","generated":true,"identifiers":["doc:\/\/SwiftMarkdownView\/documentation\/SwiftMarkdownView\/SwiftUICore"],"anchor":"Extended-Modules"}],"schemaVersion":{"major":0,"minor":3,"patch":0},"metadata":{"roleHeading":"Framework","color":{"standardColorIdentifier":"blue"},"externalID":"SwiftMarkdownView","role":"collection","symbolKind":"module","modules":[{"name":"SwiftMarkdownView"}],"title":"SwiftMarkdownView"},"abstract":[{"type":"text","text":"SwiftUIネイティブなMarkdownレンダリングライブラリ。"}],"primaryContentSections":[{"kind":"content","content":[{"anchor":"Overview","level":2,"text":"Overview","type":"heading"},{"inlineContent":[{"text":"SwiftMarkdownViewは、SwiftUIで美しいMarkdown表示を実現するライブラリです。","type":"text"},{"text":" ","type":"text"},{"type":"codeVoice","code":"AttributedString"},{"text":"と","type":"text"},{"type":"codeVoice","code":"Text"},{"text":"連結による高性能レンダリング、DesignSystemとの統合、","type":"text"},{"text":" ","type":"text"},{"text":"オプショナルな50+言語対応シンタックスハイライトを備えています。","type":"text"}],"type":"paragraph"},{"anchor":"%E7%89%B9%E5%BE%B4","level":3,"text":"特徴","type":"heading"},{"items":[{"content":[{"type":"paragraph","inlineContent":[{"type":"strong","inlineContent":[{"type":"text","text":"SwiftUIネイティブ"}]},{"type":"text","text":": "},{"type":"codeVoice","code":"AttributedString"},{"type":"text","text":"と"},{"type":"codeVoice","code":"Text"},{"type":"text","text":"連結による高性能レンダリング"}]}]},{"content":[{"type":"paragraph","inlineContent":[{"inlineContent":[{"type":"text","text":"DesignSystem統合"}],"type":"strong"},{"type":"text","text":": ColorPalette、Typography、Spacingとシームレスに連携"}]}]},{"content":[{"type":"paragraph","inlineContent":[{"inlineContent":[{"type":"text","text":"シンタックスハイライト"}],"type":"strong"},{"text":": オプショナルモジュールで50+言語対応","type":"text"}]}]},{"content":[{"inlineContent":[{"type":"strong","inlineContent":[{"type":"text","text":"Mermaidダイアグラム"}]},{"type":"text","text":": フローチャート、シーケンス図等をサポート"}],"type":"paragraph"}]},{"content":[{"type":"paragraph","inlineContent":[{"type":"strong","inlineContent":[{"text":"Aside（コールアウト）","type":"text"}]},{"type":"text","text":": Note、Warning、Tipなど24種類 + カスタム"}]}]},{"content":[{"type":"paragraph","inlineContent":[{"type":"strong","inlineContent":[{"text":"豊富な要素サポート","type":"text"}]},{"type":"text","text":": テーブル、タスクリスト、画像等"}]}]}],"type":"unorderedList"},{"anchor":"%E3%83%91%E3%83%83%E3%82%B1%E3%83%BC%E3%82%B8%E6%A7%8B%E6%88%90","level":3,"text":"パッケージ構成","type":"heading"},{"inlineContent":[{"text":"このパッケージは2つのモジュールで構成されています：","type":"text"}],"type":"paragraph"},{"rows":[[[{"inlineContent":[{"type":"text","text":"モジュール"}],"type":"paragraph"}],[{"inlineContent":[{"type":"text","text":"用途"}],"type":"paragraph"}]],[[{"inlineContent":[{"inlineContent":[{"type":"text","text":"SwiftMarkdownView"}],"type":"strong"}],"type":"paragraph"}],[{"inlineContent":[{"type":"text","text":"Markdownレンダリングのコアモジュール"}],"type":"paragraph"}]],[[{"inlineContent":[{"type":"strong","inlineContent":[{"type":"text","text":"SwiftMarkdownViewHighlightJS"}]}],"type":"paragraph"}],[{"inlineContent":[{"text":"HighlightJSによるシンタックスハイライト（オプション）","type":"text"}],"type":"paragraph"}]]],"header":"row","type":"table"},{"anchor":"%E3%82%AF%E3%82%A4%E3%83%83%E3%82%AF%E3%82%B9%E3%82%BF%E3%83%BC%E3%83%88","level":3,"text":"クイックスタート","type":"heading"},{"code":["import SwiftUI","import SwiftMarkdownView","","struct ContentView: View {","    var body: some View {","        MarkdownView(\"\"\"","        # Hello, Markdown!","","        This is a **bold** and *italic* text.","","        ```swift","        let greeting = \"Hello, World!\"","        print(greeting)","        ```","        \"\"\")","    }","}"],"syntax":"swift","type":"codeListing"},{"anchor":"%E3%82%B7%E3%83%B3%E3%82%BF%E3%83%83%E3%82%AF%E3%82%B9%E3%83%8F%E3%82%A4%E3%83%A9%E3%82%A4%E3%83%88%E3%82%92%E6%9C%89%E5%8A%B9%E3%81%AB%E3%81%99%E3%82%8B","level":3,"text":"シンタックスハイライトを有効にする","type":"heading"},{"code":["import SwiftMarkdownView","import SwiftMarkdownViewHighlightJS","","MarkdownView(source)","    .adaptiveSyntaxHighlighting()"],"syntax":"swift","type":"codeListing"}]}],"sections":[],"variants":[{"paths":["\/documentation\/swiftmarkdownview"],"traits":[{"interfaceLanguage":"swift"}]}],"kind":"symbol","references":{"doc://SwiftMarkdownView/documentation/SwiftMarkdownView/MarkdownPlaygroundView":{"url":"\/documentation\/swiftmarkdownview\/markdownplaygroundview","type":"topic","title":"MarkdownPlaygroundView","abstract":[{"text":"Interactive playground for Markdown editing and preview.","type":"text"}],"identifier":"doc:\/\/SwiftMarkdownView\/documentation\/SwiftMarkdownView\/MarkdownPlaygroundView","navigatorTitle":[{"text":"MarkdownPlaygroundView","kind":"identifier"}],"role":"symbol","kind":"symbol","fragments":[{"text":"struct","kind":"keyword"},{"text":" ","kind":"text"},{"text":"MarkdownPlaygroundView","kind":"identifier"}]},"doc://SwiftMarkdownView/documentation/SwiftMarkdownView/StripedTableStyle":{"identifier":"doc:\/\/SwiftMarkdownView\/documentation\/SwiftMarkdownView\/StripedTableStyle","role":"symbol","abstract":[{"type":"text","text":"A table style with alternating row colors for better readability."}],"fragments":[{"kind":"keyword","text":"struct"},{"kind":"text","text":" "},{"kind":"identifier","text":"StripedTableStyle"}],"url":"\/documentation\/swiftmarkdownview\/stripedtablestyle","navigatorTitle":[{"kind":"identifier","text":"StripedTableStyle"}],"title":"StripedTableStyle","kind":"symbol","type":"topic"},"doc://SwiftMarkdownView/documentation/SwiftMarkdownView/MarkdownCatalogRouter":{"title":"MarkdownCatalogRouter","fragments":[{"kind":"keyword","text":"enum"},{"kind":"text","text":" "},{"kind":"identifier","text":"MarkdownCatalogRouter"}],"url":"\/documentation\/swiftmarkdownview\/markdowncatalogrouter","kind":"symbol","type":"topic","navigatorTitle":[{"kind":"identifier","text":"MarkdownCatalogRouter"}],"identifier":"doc:\/\/SwiftMarkdownView\/documentation\/SwiftMarkdownView\/MarkdownCatalogRouter","abstract":[{"type":"text","text":"Router for navigating between catalog views."}],"role":"symbol"},"doc://SwiftMarkdownView/documentation/SwiftMarkdownView/MarkdownCatalogCategory":{"type":"topic","title":"MarkdownCatalogCategory","role":"symbol","navigatorTitle":[{"text":"MarkdownCatalogCategory","kind":"identifier"}],"identifier":"doc:\/\/SwiftMarkdownView\/documentation\/SwiftMarkdownView\/MarkdownCatalogCategory","fragments":[{"text":"enum","kind":"keyword"},{"text":" ","kind":"text"},{"text":"MarkdownCatalogCategory","kind":"identifier"}],"kind":"symbol","url":"\/documentation\/swiftmarkdownview\/markdowncatalogcategory","abstract":[{"type":"text","text":"Categories for the Markdown catalog."}]},"doc://SwiftMarkdownView/documentation/SwiftMarkdownView/DefaultAsideStyle":{"kind":"symbol","identifier":"doc:\/\/SwiftMarkdownView\/documentation\/SwiftMarkdownView\/DefaultAsideStyle","abstract":[{"type":"text","text":"The default aside style with semantic colors for common aside kinds."}],"title":"DefaultAsideStyle","fragments":[{"text":"struct","kind":"keyword"},{"text":" ","kind":"text"},{"text":"DefaultAsideStyle","kind":"identifier"}],"type":"topic","role":"symbol","url":"\/documentation\/swiftmarkdownview\/defaultasidestyle","navigatorTitle":[{"text":"DefaultAsideStyle","kind":"identifier"}]},"doc://SwiftMarkdownView/documentation/SwiftMarkdownView/MermaidScriptProvider":{"navigatorTitle":[{"text":"MermaidScriptProvider","kind":"identifier"}],"fragments":[{"text":"protocol","kind":"keyword"},{"text":" ","kind":"text"},{"text":"MermaidScriptProvider","kind":"identifier"}],"identifier":"doc:\/\/SwiftMarkdownView\/documentation\/SwiftMarkdownView\/MermaidScriptProvider","role":"symbol","abstract":[{"type":"text","text":"A protocol that defines how to provide the Mermaid.js script for diagram rendering."}],"kind":"symbol","title":"MermaidScriptProvider","type":"topic","url":"\/documentation\/swiftmarkdownview\/mermaidscriptprovider"},"doc://SwiftMarkdownView/documentation/SwiftMarkdownView/UnorderedListCatalogView":{"navigatorTitle":[{"text":"UnorderedListCatalogView","kind":"identifier"}],"role":"symbol","title":"UnorderedListCatalogView","abstract":[{"type":"text","text":"Catalog view for unordered (bulleted) list elements."}],"kind":"symbol","url":"\/documentation\/swiftmarkdownview\/unorderedlistcatalogview","identifier":"doc:\/\/SwiftMarkdownView\/documentation\/SwiftMarkdownView\/UnorderedListCatalogView","type":"topic","fragments":[{"text":"struct","kind":"keyword"},{"text":" ","kind":"text"},{"text":"UnorderedListCatalogView","kind":"identifier"}]},"doc://SwiftMarkdownView/documentation/SwiftMarkdownView/AsideKind":{"navigatorTitle":[{"text":"AsideKind","kind":"identifier"}],"role":"symbol","fragments":[{"text":"enum","kind":"keyword"},{"text":" ","kind":"text"},{"text":"AsideKind","kind":"identifier"}],"url":"\/documentation\/swiftmarkdownview\/asidekind","identifier":"doc:\/\/SwiftMarkdownView\/documentation\/SwiftMarkdownView\/AsideKind","abstract":[{"type":"text","text":"The kind of aside (callout\/admonition)."}],"type":"topic","title":"AsideKind","kind":"symbol"},"doc://SwiftMarkdownView/documentation/SwiftMarkdownView/CodeBlockStyleCatalogView":{"identifier":"doc:\/\/SwiftMarkdownView\/documentation\/SwiftMarkdownView\/CodeBlockStyleCatalogView","kind":"symbol","role":"symbol","fragments":[{"text":"struct","kind":"keyword"},{"text":" ","kind":"text"},{"text":"CodeBlockStyleCatalogView","kind":"identifier"}],"url":"\/documentation\/swiftmarkdownview\/codeblockstylecatalogview","title":"CodeBlockStyleCatalogView","navigatorTitle":[{"text":"CodeBlockStyleCatalogView","kind":"identifier"}],"abstract":[{"type":"text","text":"Catalog view for CodeBlockStyle configuration."}],"type":"topic"},"doc://SwiftMarkdownView/documentation/SwiftMarkdownView/CDNMermaidScriptProvider":{"type":"topic","abstract":[{"type":"text","text":"A Mermaid script provider that loads from jsDelivr CDN."}],"fragments":[{"kind":"keyword","text":"struct"},{"kind":"text","text":" "},{"kind":"identifier","text":"CDNMermaidScriptProvider"}],"navigatorTitle":[{"kind":"identifier","text":"CDNMermaidScriptProvider"}],"role":"symbol","identifier":"doc:\/\/SwiftMarkdownView\/documentation\/SwiftMarkdownView\/CDNMermaidScriptProvider","title":"CDNMermaidScriptProvider","url":"\/documentation\/swiftmarkdownview\/cdnmermaidscriptprovider","kind":"symbol"},"doc://SwiftMarkdownView/documentation/SwiftMarkdownView/MarkdownRenderingOptions":{"role":"symbol","abstract":[{"type":"text","text":"Options for controlling Markdown rendering behavior."}],"fragments":[{"text":"struct","kind":"keyword"},{"text":" ","kind":"text"},{"text":"MarkdownRenderingOptions","kind":"identifier"}],"type":"topic","kind":"symbol","title":"MarkdownRenderingOptions","url":"\/documentation\/swiftmarkdownview\/markdownrenderingoptions","identifier":"doc:\/\/SwiftMarkdownView\/documentation\/SwiftMarkdownView\/MarkdownRenderingOptions","navigatorTitle":[{"text":"MarkdownRenderingOptions","kind":"identifier"}]},"doc://SwiftMarkdownView/documentation/SwiftMarkdownView/defaultMermaidScriptProvider":{"identifier":"doc:\/\/SwiftMarkdownView\/documentation\/SwiftMarkdownView\/defaultMermaidScriptProvider","abstract":[{"type":"text","text":"The default Mermaid script provider (CDN-based)."}],"title":"defaultMermaidScriptProvider","type":"topic","fragments":[{"kind":"keyword","text":"let"},{"kind":"text","text":" "},{"kind":"identifier","text":"defaultMermaidScriptProvider"},{"kind":"text","text":": any "},{"kind":"typeIdentifier","preciseIdentifier":"s:17SwiftMarkdownView21MermaidScriptProviderP","text":"MermaidScriptProvider"}],"url":"\/documentation\/swiftmarkdownview\/defaultmermaidscriptprovider","role":"symbol","kind":"symbol"},"doc://SwiftMarkdownView/documentation/SwiftMarkdownView/HeadingStyleCatalogView":{"kind":"symbol","url":"\/documentation\/swiftmarkdownview\/headingstylecatalogview","type":"topic","navigatorTitle":[{"kind":"identifier","text":"HeadingStyleCatalogView"}],"abstract":[{"type":"text","text":"Catalog view for HeadingStyle configuration."}],"title":"HeadingStyleCatalogView","identifier":"doc:\/\/SwiftMarkdownView\/documentation\/SwiftMarkdownView\/HeadingStyleCatalogView","role":"symbol","fragments":[{"kind":"keyword","text":"struct"},{"kind":"text","text":" "},{"kind":"identifier","text":"HeadingStyleCatalogView"}]},"doc://SwiftMarkdownView/documentation/SwiftMarkdownView/BoldLinkStyle":{"identifier":"doc:\/\/SwiftMarkdownView\/documentation\/SwiftMarkdownView\/BoldLinkStyle","url":"\/documentation\/swiftmarkdownview\/boldlinkstyle","role":"symbol","fragments":[{"text":"struct","kind":"keyword"},{"text":" ","kind":"text"},{"text":"BoldLinkStyle","kind":"identifier"}],"title":"BoldLinkStyle","abstract":[{"type":"text","text":"A bold link style with emphasis."}],"kind":"symbol","type":"topic","navigatorTitle":[{"text":"BoldLinkStyle","kind":"identifier"}]},"doc://SwiftMarkdownView/documentation/SwiftMarkdownView/ClassicLinkStyle":{"kind":"symbol","url":"\/documentation\/swiftmarkdownview\/classiclinkstyle","title":"ClassicLinkStyle","role":"symbol","navigatorTitle":[{"kind":"identifier","text":"ClassicLinkStyle"}],"fragments":[{"kind":"keyword","text":"struct"},{"kind":"text","text":" "},{"kind":"identifier","text":"ClassicLinkStyle"}],"abstract":[{"text":"A classic web-style link appearance.","type":"text"}],"type":"topic","identifier":"doc:\/\/SwiftMarkdownView\/documentation\/SwiftMarkdownView\/ClassicLinkStyle"},"doc://SwiftMarkdownView/documentation/SwiftMarkdownView/MarkdownCatalogItem":{"type":"topic","role":"symbol","navigatorTitle":[{"text":"MarkdownCatalogItem","kind":"identifier"}],"title":"MarkdownCatalogItem","fragments":[{"text":"struct","kind":"keyword"},{"text":" ","kind":"text"},{"text":"MarkdownCatalogItem","kind":"identifier"}],"abstract":[{"type":"text","text":"A single item in the Markdown catalog."}],"kind":"symbol","identifier":"doc:\/\/SwiftMarkdownView\/documentation\/SwiftMarkdownView\/MarkdownCatalogItem","url":"\/documentation\/swiftmarkdownview\/markdowncatalogitem"},"doc://SwiftMarkdownView/documentation/SwiftMarkdownView/ListItem":{"role":"symbol","fragments":[{"text":"struct","kind":"keyword"},{"text":" ","kind":"text"},{"text":"ListItem","kind":"identifier"}],"url":"\/documentation\/swiftmarkdownview\/listitem","identifier":"doc:\/\/SwiftMarkdownView\/documentation\/SwiftMarkdownView\/ListItem","navigatorTitle":[{"text":"ListItem","kind":"identifier"}],"title":"ListItem","type":"topic","abstract":[{"text":"An item in a list, which can contain nested blocks.","type":"text"}],"kind":"symbol"},"doc://SwiftMarkdownView/documentation/SwiftMarkdownView/DefaultLinkStyle":{"title":"DefaultLinkStyle","role":"symbol","fragments":[{"kind":"keyword","text":"struct"},{"kind":"text","text":" "},{"kind":"identifier","text":"DefaultLinkStyle"}],"type":"topic","identifier":"doc:\/\/SwiftMarkdownView\/documentation\/SwiftMarkdownView\/DefaultLinkStyle","kind":"symbol","abstract":[{"text":"The default link style using the primary color with underline.","type":"text"}],"url":"\/documentation\/swiftmarkdownview\/defaultlinkstyle","navigatorTitle":[{"kind":"identifier","text":"DefaultLinkStyle"}]},"doc://SwiftMarkdownView/documentation/SwiftMarkdownView/BlockElementItem":{"role":"symbol","navigatorTitle":[{"text":"BlockElementItem","kind":"identifier"}],"title":"BlockElementItem","type":"topic","kind":"symbol","url":"\/documentation\/swiftmarkdownview\/blockelementitem","abstract":[{"type":"text","text":"Block-level element types for the catalog."}],"fragments":[{"text":"enum","kind":"keyword"},{"text":" ","kind":"text"},{"text":"BlockElementItem","kind":"identifier"}],"identifier":"doc:\/\/SwiftMarkdownView\/documentation\/SwiftMarkdownView\/BlockElementItem"},"doc://SwiftMarkdownView/documentation/SwiftMarkdownView/Asides":{"title":"Aside（コールアウト）","role":"article","identifier":"doc:\/\/SwiftMarkdownView\/documentation\/SwiftMarkdownView\/Asides","url":"\/documentation\/swiftmarkdownview\/asides","abstract":[{"text":"ブロッククォートをNote、Warning、Tipなどのコールアウトとして表示する方法を学びます。","type":"text"}],"kind":"article","type":"topic"},"doc://SwiftMarkdownView/documentation/SwiftMarkdownView/RenderingOptionsCatalogView":{"role":"symbol","url":"\/documentation\/swiftmarkdownview\/renderingoptionscatalogview","navigatorTitle":[{"kind":"identifier","text":"RenderingOptionsCatalogView"}],"identifier":"doc:\/\/SwiftMarkdownView\/documentation\/SwiftMarkdownView\/RenderingOptionsCatalogView","abstract":[{"type":"text","text":"Catalog view for MarkdownRenderingOptions configuration."}],"type":"topic","kind":"symbol","fragments":[{"kind":"keyword","text":"struct"},{"kind":"text","text":" "},{"kind":"identifier","text":"RenderingOptionsCatalogView"}],"title":"RenderingOptionsCatalogView"},"doc://SwiftMarkdownView/documentation/SwiftMarkdownView/TableAlignment":{"kind":"symbol","abstract":[{"type":"text","text":"Column alignment options for tables."}],"fragments":[{"kind":"keyword","text":"enum"},{"kind":"text","text":" "},{"kind":"identifier","text":"TableAlignment"}],"navigatorTitle":[{"kind":"identifier","text":"TableAlignment"}],"identifier":"doc:\/\/SwiftMarkdownView\/documentation\/SwiftMarkdownView\/TableAlignment","role":"symbol","type":"topic","title":"TableAlignment","url":"\/documentation\/swiftmarkdownview\/tablealignment"},"doc://SwiftMarkdownView/documentation/SwiftMarkdownView/TableStyle":{"identifier":"doc:\/\/SwiftMarkdownView\/documentation\/SwiftMarkdownView\/TableStyle","abstract":[{"text":"A protocol that defines the visual styling for tables.","type":"text"}],"type":"topic","title":"TableStyle","kind":"symbol","url":"\/documentation\/swiftmarkdownview\/tablestyle","role":"symbol","fragments":[{"kind":"keyword","text":"protocol"},{"kind":"text","text":" "},{"kind":"identifier","text":"TableStyle"}],"navigatorTitle":[{"kind":"identifier","text":"TableStyle"}]},"doc://SwiftMarkdownView/documentation/SwiftMarkdownView/SyntaxHighlighter":{"url":"\/documentation\/swiftmarkdownview\/syntaxhighlighter","identifier":"doc:\/\/SwiftMarkdownView\/documentation\/SwiftMarkdownView\/SyntaxHighlighter","abstract":[{"type":"text","text":"A type that can highlight source code asynchronously."}],"title":"SyntaxHighlighter","role":"symbol","navigatorTitle":[{"text":"SyntaxHighlighter","kind":"identifier"}],"kind":"symbol","type":"topic","fragments":[{"text":"protocol","kind":"keyword"},{"text":" ","kind":"text"},{"text":"SyntaxHighlighter","kind":"identifier"}]},"doc://SwiftMarkdownView/documentation/SwiftMarkdownView/InlineElementItem":{"url":"\/documentation\/swiftmarkdownview\/inlineelementitem","navigatorTitle":[{"text":"InlineElementItem","kind":"identifier"}],"title":"InlineElementItem","role":"symbol","type":"topic","identifier":"doc:\/\/SwiftMarkdownView\/documentation\/SwiftMarkdownView\/InlineElementItem","kind":"symbol","abstract":[{"type":"text","text":"Inline element types for the catalog."}],"fragments":[{"text":"enum","kind":"keyword"},{"text":" ","kind":"text"},{"text":"InlineElementItem","kind":"identifier"}]},"doc://SwiftMarkdownView/documentation/SwiftMarkdownView/MarkdownTypographyMapping":{"abstract":[{"type":"text","text":"Maps Markdown heading levels to DesignSystem Typography tokens."}],"type":"topic","fragments":[{"kind":"keyword","text":"enum"},{"kind":"text","text":" "},{"kind":"identifier","text":"MarkdownTypographyMapping"}],"url":"\/documentation\/swiftmarkdownview\/markdowntypographymapping","kind":"symbol","identifier":"doc:\/\/SwiftMarkdownView\/documentation\/SwiftMarkdownView\/MarkdownTypographyMapping","title":"MarkdownTypographyMapping","role":"symbol","navigatorTitle":[{"kind":"identifier","text":"MarkdownTypographyMapping"}]},"doc://SwiftMarkdownView/documentation/SwiftMarkdownView/CatalogSectionCard":{"url":"\/documentation\/swiftmarkdownview\/catalogsectioncard","kind":"symbol","abstract":[{"type":"text","text":"A section card for organizing catalog content."}],"identifier":"doc:\/\/SwiftMarkdownView\/documentation\/SwiftMarkdownView\/CatalogSectionCard","title":"CatalogSectionCard","role":"symbol","fragments":[{"text":"struct","kind":"keyword"},{"text":" ","kind":"text"},{"text":"CatalogSectionCard","kind":"identifier"}],"navigatorTitle":[{"text":"CatalogSectionCard","kind":"identifier"}],"type":"topic"},"doc://SwiftMarkdownView/documentation/SwiftMarkdownView/MarkdownContent":{"url":"\/documentation\/swiftmarkdownview\/markdowncontent","abstract":[{"text":"A parsed Markdown document represented as a collection of blocks.","type":"text"}],"title":"MarkdownContent","role":"symbol","fragments":[{"text":"struct","kind":"keyword"},{"text":" ","kind":"text"},{"text":"MarkdownContent","kind":"identifier"}],"kind":"symbol","identifier":"doc:\/\/SwiftMarkdownView\/documentation\/SwiftMarkdownView\/MarkdownContent","navigatorTitle":[{"text":"MarkdownContent","kind":"identifier"}],"type":"topic"},"doc://SwiftMarkdownView/documentation/SwiftMarkdownView/MermaidFallbackView":{"fragments":[{"text":"struct","kind":"keyword"},{"text":" ","kind":"text"},{"text":"MermaidFallbackView","kind":"identifier"}],"type":"topic","kind":"symbol","identifier":"doc:\/\/SwiftMarkdownView\/documentation\/SwiftMarkdownView\/MermaidFallbackView","navigatorTitle":[{"text":"MermaidFallbackView","kind":"identifier"}],"url":"\/documentation\/swiftmarkdownview\/mermaidfallbackview","role":"symbol","abstract":[{"type":"text","text":"A placeholder view for Mermaid diagrams on older OS versions."}],"title":"MermaidFallbackView"},"doc://SwiftMarkdownView/documentation/SwiftMarkdownView/CardTableStyle":{"navigatorTitle":[{"kind":"identifier","text":"CardTableStyle"}],"fragments":[{"kind":"keyword","text":"struct"},{"kind":"text","text":" "},{"kind":"identifier","text":"CardTableStyle"}],"url":"\/documentation\/swiftmarkdownview\/cardtablestyle","abstract":[{"text":"A table style that looks like a card with rounded corners and shadow.","type":"text"}],"role":"symbol","identifier":"doc:\/\/SwiftMarkdownView\/documentation\/SwiftMarkdownView\/CardTableStyle","title":"CardTableStyle","kind":"symbol","type":"topic"},"doc://SwiftMarkdownView/documentation/SwiftMarkdownView/ColoredHeadingStyle":{"abstract":[{"type":"text","text":"A heading style with colored primary headings."}],"role":"symbol","fragments":[{"text":"struct","kind":"keyword"},{"text":" ","kind":"text"},{"text":"ColoredHeadingStyle","kind":"identifier"}],"identifier":"doc:\/\/SwiftMarkdownView\/documentation\/SwiftMarkdownView\/ColoredHeadingStyle","url":"\/documentation\/swiftmarkdownview\/coloredheadingstyle","title":"ColoredHeadingStyle","kind":"symbol","navigatorTitle":[{"text":"ColoredHeadingStyle","kind":"identifier"}],"type":"topic"},"doc://SwiftMarkdownView/documentation/SwiftMarkdownView/AsideStyleCatalogView":{"navigatorTitle":[{"text":"AsideStyleCatalogView","kind":"identifier"}],"fragments":[{"text":"struct","kind":"keyword"},{"text":" ","kind":"text"},{"text":"AsideStyleCatalogView","kind":"identifier"}],"identifier":"doc:\/\/SwiftMarkdownView\/documentation\/SwiftMarkdownView\/AsideStyleCatalogView","abstract":[{"type":"text","text":"Catalog view for AsideStyle configuration."}],"kind":"symbol","type":"topic","title":"AsideStyleCatalogView","role":"symbol","url":"\/documentation\/swiftmarkdownview\/asidestylecatalogview"},"doc://SwiftMarkdownView/documentation/SwiftMarkdownView/DividedHeadingStyle":{"role":"symbol","abstract":[{"text":"A heading style with dividers below H1 and H2 headings.","type":"text"}],"identifier":"doc:\/\/SwiftMarkdownView\/documentation\/SwiftMarkdownView\/DividedHeadingStyle","title":"DividedHeadingStyle","kind":"symbol","fragments":[{"kind":"keyword","text":"struct"},{"kind":"text","text":" "},{"kind":"identifier","text":"DividedHeadingStyle"}],"url":"\/documentation\/swiftmarkdownview\/dividedheadingstyle","type":"topic","navigatorTitle":[{"kind":"identifier","text":"DividedHeadingStyle"}]},"doc://SwiftMarkdownView/documentation/SwiftMarkdownView/MermaidCatalogView":{"identifier":"doc:\/\/SwiftMarkdownView\/documentation\/SwiftMarkdownView\/MermaidCatalogView","role":"symbol","title":"MermaidCatalogView","abstract":[{"text":"Catalog view for Mermaid diagram elements.","type":"text"}],"url":"\/documentation\/swiftmarkdownview\/mermaidcatalogview","fragments":[{"text":"struct","kind":"keyword"},{"text":" ","kind":"text"},{"text":"MermaidCatalogView","kind":"identifier"}],"navigatorTitle":[{"text":"MermaidCatalogView","kind":"identifier"}],"kind":"symbol","type":"topic"},"doc://SwiftMarkdownView/documentation/SwiftMarkdownView/PlainTextHighlighter":{"identifier":"doc:\/\/SwiftMarkdownView\/documentation\/SwiftMarkdownView\/PlainTextHighlighter","type":"topic","title":"PlainTextHighlighter","kind":"symbol","abstract":[{"type":"text","text":"A plain text highlighter that applies no syntax highlighting."}],"fragments":[{"text":"struct","kind":"keyword"},{"text":" ","kind":"text"},{"text":"PlainTextHighlighter","kind":"identifier"}],"role":"symbol","url":"\/documentation\/swiftmarkdownview\/plaintexthighlighter","navigatorTitle":[{"text":"PlainTextHighlighter","kind":"identifier"}]},"doc://SwiftMarkdownView/documentation/SwiftMarkdownView/AsideStyle":{"fragments":[{"text":"protocol","kind":"keyword"},{"text":" ","kind":"text"},{"text":"AsideStyle","kind":"identifier"}],"type":"topic","title":"AsideStyle","role":"symbol","url":"\/documentation\/swiftmarkdownview\/asidestyle","abstract":[{"type":"text","text":"A protocol that defines the visual styling for aside blocks."}],"kind":"symbol","navigatorTitle":[{"text":"AsideStyle","kind":"identifier"}],"identifier":"doc:\/\/SwiftMarkdownView\/documentation\/SwiftMarkdownView\/AsideStyle"},"doc://SwiftMarkdownView/documentation/SwiftMarkdownView/DesignSystemItem":{"navigatorTitle":[{"text":"DesignSystemItem","kind":"identifier"}],"identifier":"doc:\/\/SwiftMarkdownView\/documentation\/SwiftMarkdownView\/DesignSystemItem","fragments":[{"text":"enum","kind":"keyword"},{"text":" ","kind":"text"},{"text":"DesignSystemItem","kind":"identifier"}],"title":"DesignSystemItem","role":"symbol","type":"topic","kind":"symbol","abstract":[{"type":"text","text":"DesignSystem integration items for the catalog."}],"url":"\/documentation\/swiftmarkdownview\/designsystemitem"},"doc://SwiftMarkdownView/documentation/SwiftMarkdownView/ThematicBreakCatalogView":{"fragments":[{"text":"struct","kind":"keyword"},{"text":" ","kind":"text"},{"text":"ThematicBreakCatalogView","kind":"identifier"}],"abstract":[{"type":"text","text":"Catalog view for thematic break (horizontal rule) elements."}],"role":"symbol","identifier":"doc:\/\/SwiftMarkdownView\/documentation\/SwiftMarkdownView\/ThematicBreakCatalogView","type":"topic","title":"ThematicBreakCatalogView","kind":"symbol","navigatorTitle":[{"text":"ThematicBreakCatalogView","kind":"identifier"}],"url":"\/documentation\/swiftmarkdownview\/thematicbreakcatalogview"},"doc://SwiftMarkdownView/documentation/SwiftMarkdownView/HighlightState":{"url":"\/documentation\/swiftmarkdownview\/highlightstate","fragments":[{"text":"enum","kind":"keyword"},{"text":" ","kind":"text"},{"text":"HighlightState","kind":"identifier"}],"abstract":[{"text":"The state of a syntax highlighting operation.","type":"text"}],"title":"HighlightState","type":"topic","role":"symbol","identifier":"doc:\/\/SwiftMarkdownView\/documentation\/SwiftMarkdownView\/HighlightState","kind":"symbol","navigatorTitle":[{"text":"HighlightState","kind":"identifier"}]},"doc://SwiftMarkdownView/documentation/SwiftMarkdownView/MarkdownRadius":{"role":"symbol","title":"MarkdownRadius","fragments":[{"kind":"keyword","text":"enum"},{"kind":"text","text":" "},{"kind":"identifier","text":"MarkdownRadius"}],"url":"\/documentation\/swiftmarkdownview\/markdownradius","navigatorTitle":[{"kind":"identifier","text":"MarkdownRadius"}],"kind":"symbol","identifier":"doc:\/\/SwiftMarkdownView\/documentation\/SwiftMarkdownView\/MarkdownRadius","type":"topic","abstract":[{"text":"Corner radius values for Markdown elements.","type":"text"}]},"doc://SwiftMarkdownView/documentation/SwiftMarkdownView/MarkdownInline":{"url":"\/documentation\/swiftmarkdownview\/markdowninline","kind":"symbol","title":"MarkdownInline","fragments":[{"kind":"keyword","text":"enum"},{"kind":"text","text":" "},{"kind":"identifier","text":"MarkdownInline"}],"identifier":"doc:\/\/SwiftMarkdownView\/documentation\/SwiftMarkdownView\/MarkdownInline","abstract":[{"type":"text","text":"An inline element within a Markdown block."}],"role":"symbol","navigatorTitle":[{"kind":"identifier","text":"MarkdownInline"}],"type":"topic"},"doc://SwiftMarkdownView/documentation/SwiftMarkdownView/TextStylesCatalogView":{"role":"symbol","kind":"symbol","title":"TextStylesCatalogView","url":"\/documentation\/swiftmarkdownview\/textstylescatalogview","abstract":[{"type":"text","text":"Catalog view for text style elements (bold, italic, strikethrough)."}],"identifier":"doc:\/\/SwiftMarkdownView\/documentation\/SwiftMarkdownView\/TextStylesCatalogView","navigatorTitle":[{"text":"TextStylesCatalogView","kind":"identifier"}],"fragments":[{"text":"struct","kind":"keyword"},{"text":" ","kind":"text"},{"text":"TextStylesCatalogView","kind":"identifier"}],"type":"topic"},"doc://SwiftMarkdownView/documentation/SwiftMarkdownView/SoftBreakCatalogView":{"identifier":"doc:\/\/SwiftMarkdownView\/documentation\/SwiftMarkdownView\/SoftBreakCatalogView","abstract":[{"type":"text","text":"Catalog view for line break elements."}],"title":"SoftBreakCatalogView","type":"topic","role":"symbol","fragments":[{"text":"struct","kind":"keyword"},{"text":" ","kind":"text"},{"text":"SoftBreakCatalogView","kind":"identifier"}],"navigatorTitle":[{"text":"SoftBreakCatalogView","kind":"identifier"}],"url":"\/documentation\/swiftmarkdownview\/softbreakcatalogview","kind":"symbol"},"doc://SwiftMarkdownView/documentation/SwiftMarkdownView":{"identifier":"doc:\/\/SwiftMarkdownView\/documentation\/SwiftMarkdownView","type":"topic","abstract":[{"type":"text","text":"SwiftUIネイティブなMarkdownレンダリングライブラリ。"}],"url":"\/documentation\/swiftmarkdownview","kind":"symbol","title":"SwiftMarkdownView","role":"collection"},"doc://SwiftMarkdownView/documentation/SwiftMarkdownView/DefaultTableStyle":{"abstract":[{"type":"text","text":"The default table style with subtle borders and header highlighting."}],"kind":"symbol","url":"\/documentation\/swiftmarkdownview\/defaulttablestyle","role":"symbol","fragments":[{"text":"struct","kind":"keyword"},{"text":" ","kind":"text"},{"text":"DefaultTableStyle","kind":"identifier"}],"identifier":"doc:\/\/SwiftMarkdownView\/documentation\/SwiftMarkdownView\/DefaultTableStyle","navigatorTitle":[{"text":"DefaultTableStyle","kind":"identifier"}],"title":"DefaultTableStyle","type":"topic"},"doc://SwiftMarkdownView/documentation/SwiftMarkdownView/ParagraphCatalogView":{"title":"ParagraphCatalogView","abstract":[{"text":"Catalog view for paragraph elements.","type":"text"}],"fragments":[{"text":"struct","kind":"keyword"},{"text":" ","kind":"text"},{"text":"ParagraphCatalogView","kind":"identifier"}],"role":"symbol","url":"\/documentation\/swiftmarkdownview\/paragraphcatalogview","kind":"symbol","identifier":"doc:\/\/SwiftMarkdownView\/documentation\/SwiftMarkdownView\/ParagraphCatalogView","type":"topic","navigatorTitle":[{"text":"ParagraphCatalogView","kind":"identifier"}]},"doc://SwiftMarkdownView/documentation/SwiftMarkdownView/TableData":{"abstract":[{"type":"text","text":"Represents a complete table structure."}],"kind":"symbol","identifier":"doc:\/\/SwiftMarkdownView\/documentation\/SwiftMarkdownView\/TableData","url":"\/documentation\/swiftmarkdownview\/tabledata","type":"topic","title":"TableData","role":"symbol","fragments":[{"text":"struct","kind":"keyword"},{"text":" ","kind":"text"},{"text":"TableData","kind":"identifier"}],"navigatorTitle":[{"text":"TableData","kind":"identifier"}]},"doc://SwiftMarkdownView/documentation/SwiftMarkdownView/AsideCatalogView":{"fragments":[{"text":"struct","kind":"keyword"},{"text":" ","kind":"text"},{"text":"AsideCatalogView","kind":"identifier"}],"kind":"symbol","navigatorTitle":[{"text":"AsideCatalogView","kind":"identifier"}],"type":"topic","role":"symbol","abstract":[{"type":"text","text":"Catalog view for aside (callout\/admonition) elements."}],"identifier":"doc:\/\/SwiftMarkdownView\/documentation\/SwiftMarkdownView\/AsideCatalogView","title":"AsideCatalogView","url":"\/documentation\/swiftmarkdownview\/asidecatalogview"},"doc://SwiftMarkdownView/documentation/SwiftMarkdownView/SyntaxHighlighterCatalogView":{"role":"symbol","fragments":[{"kind":"keyword","text":"struct"},{"kind":"text","text":" "},{"kind":"identifier","text":"SyntaxHighlighterCatalogView"}],"navigatorTitle":[{"kind":"identifier","text":"SyntaxHighlighterCatalogView"}],"url":"\/documentation\/swiftmarkdownview\/syntaxhighlightercatalogview","kind":"symbol","title":"SyntaxHighlighterCatalogView","type":"topic","identifier":"doc:\/\/SwiftMarkdownView\/documentation\/SwiftMarkdownView\/SyntaxHighlighterCatalogView","abstract":[{"type":"text","text":"Catalog view for SyntaxHighlighter configuration."}]},"doc://SwiftMarkdownView/documentation/SwiftMarkdownView/CodeBlockStyle":{"fragments":[{"text":"protocol","kind":"keyword"},{"text":" ","kind":"text"},{"text":"CodeBlockStyle","kind":"identifier"}],"url":"\/documentation\/swiftmarkdownview\/codeblockstyle","navigatorTitle":[{"text":"CodeBlockStyle","kind":"identifier"}],"role":"symbol","abstract":[{"type":"text","text":"A protocol that defines the visual styling for code blocks."}],"title":"CodeBlockStyle","kind":"symbol","type":"topic","identifier":"doc:\/\/SwiftMarkdownView\/documentation\/SwiftMarkdownView\/CodeBlockStyle"},"doc://SwiftMarkdownView/documentation/SwiftMarkdownView/MarkdownPreviewCard":{"identifier":"doc:\/\/SwiftMarkdownView\/documentation\/SwiftMarkdownView\/MarkdownPreviewCard","title":"MarkdownPreviewCard","type":"topic","url":"\/documentation\/swiftmarkdownview\/markdownpreviewcard","fragments":[{"text":"struct","kind":"keyword"},{"text":" ","kind":"text"},{"text":"MarkdownPreviewCard","kind":"identifier"}],"abstract":[{"type":"text","text":"A card that displays Markdown source and its rendered preview."}],"kind":"symbol","role":"symbol","navigatorTitle":[{"text":"MarkdownPreviewCard","kind":"identifier"}]},"doc://SwiftMarkdownView/documentation/SwiftMarkdownView/CodeBlockCatalogView":{"identifier":"doc:\/\/SwiftMarkdownView\/documentation\/SwiftMarkdownView\/CodeBlockCatalogView","type":"topic","title":"CodeBlockCatalogView","role":"symbol","abstract":[{"text":"Catalog view for code block elements.","type":"text"}],"fragments":[{"text":"struct","kind":"keyword"},{"text":" ","kind":"text"},{"text":"CodeBlockCatalogView","kind":"identifier"}],"navigatorTitle":[{"text":"CodeBlockCatalogView","kind":"identifier"}],"url":"\/documentation\/swiftmarkdownview\/codeblockcatalogview","kind":"symbol"},"doc://SwiftMarkdownView/documentation/SwiftMarkdownView/MarkdownSpacing":{"role":"symbol","url":"\/documentation\/swiftmarkdownview\/markdownspacing","abstract":[{"text":"Spacing values for Markdown layout using DesignSystem tokens.","type":"text"}],"kind":"symbol","title":"MarkdownSpacing","type":"topic","fragments":[{"kind":"keyword","text":"enum"},{"kind":"text","text":" "},{"kind":"identifier","text":"MarkdownSpacing"}],"identifier":"doc:\/\/SwiftMarkdownView\/documentation\/SwiftMarkdownView\/MarkdownSpacing","navigatorTitle":[{"kind":"identifier","text":"MarkdownSpacing"}]},"doc://SwiftMarkdownView/documentation/SwiftMarkdownView/DefaultHeadingStyle":{"fragments":[{"text":"struct","kind":"keyword"},{"text":" ","kind":"text"},{"text":"DefaultHeadingStyle","kind":"identifier"}],"title":"DefaultHeadingStyle","identifier":"doc:\/\/SwiftMarkdownView\/documentation\/SwiftMarkdownView\/DefaultHeadingStyle","url":"\/documentation\/swiftmarkdownview\/defaultheadingstyle","navigatorTitle":[{"text":"DefaultHeadingStyle","kind":"identifier"}],"type":"topic","abstract":[{"text":"The default heading style using DesignSystem typography tokens.","type":"text"}],"kind":"symbol","role":"symbol"},"doc://SwiftMarkdownView/documentation/SwiftMarkdownView/ConfigurationItem":{"identifier":"doc:\/\/SwiftMarkdownView\/documentation\/SwiftMarkdownView\/ConfigurationItem","kind":"symbol","abstract":[{"text":"Configuration and style options for the catalog.","type":"text"}],"url":"\/documentation\/swiftmarkdownview\/configurationitem","type":"topic","fragments":[{"kind":"keyword","text":"enum"},{"kind":"text","text":" "},{"kind":"identifier","text":"ConfigurationItem"}],"role":"symbol","navigatorTitle":[{"kind":"identifier","text":"ConfigurationItem"}],"title":"ConfigurationItem"},"doc://SwiftMarkdownView/documentation/SwiftMarkdownView/MermaidScriptSource":{"kind":"symbol","type":"topic","title":"MermaidScriptSource","abstract":[{"type":"text","text":"Represents the source of the Mermaid.js script."}],"role":"symbol","identifier":"doc:\/\/SwiftMarkdownView\/documentation\/SwiftMarkdownView\/MermaidScriptSource","url":"\/documentation\/swiftmarkdownview\/mermaidscriptsource","fragments":[{"text":"enum","kind":"keyword"},{"text":" ","kind":"text"},{"text":"MermaidScriptSource","kind":"identifier"}],"navigatorTitle":[{"text":"MermaidScriptSource","kind":"identifier"}]},"doc://SwiftMarkdownView/documentation/SwiftMarkdownView/MarkdownBlock":{"title":"MarkdownBlock","kind":"symbol","fragments":[{"kind":"keyword","text":"enum"},{"kind":"text","text":" "},{"kind":"identifier","text":"MarkdownBlock"}],"url":"\/documentation\/swiftmarkdownview\/markdownblock","role":"symbol","navigatorTitle":[{"kind":"identifier","text":"MarkdownBlock"}],"identifier":"doc:\/\/SwiftMarkdownView\/documentation\/SwiftMarkdownView\/MarkdownBlock","type":"topic","abstract":[{"type":"text","text":"A block-level element in a Markdown document."}]},"doc://SwiftMarkdownView/documentation/SwiftMarkdownView/HeadingCatalogView":{"kind":"symbol","abstract":[{"text":"Catalog view for heading elements (H1-H6).","type":"text"}],"type":"topic","fragments":[{"kind":"keyword","text":"struct"},{"kind":"text","text":" "},{"kind":"identifier","text":"HeadingCatalogView"}],"role":"symbol","url":"\/documentation\/swiftmarkdownview\/headingcatalogview","navigatorTitle":[{"kind":"identifier","text":"HeadingCatalogView"}],"identifier":"doc:\/\/SwiftMarkdownView\/documentation\/SwiftMarkdownView\/HeadingCatalogView","title":"HeadingCatalogView"},"doc://SwiftMarkdownView/documentation/SwiftMarkdownView/LinkCatalogView":{"fragments":[{"text":"struct","kind":"keyword"},{"text":" ","kind":"text"},{"text":"LinkCatalogView","kind":"identifier"}],"type":"topic","url":"\/documentation\/swiftmarkdownview\/linkcatalogview","title":"LinkCatalogView","abstract":[{"text":"Catalog view for link elements.","type":"text"}],"identifier":"doc:\/\/SwiftMarkdownView\/documentation\/SwiftMarkdownView\/LinkCatalogView","kind":"symbol","role":"symbol","navigatorTitle":[{"text":"LinkCatalogView","kind":"identifier"}]},"doc://SwiftMarkdownView/documentation/SwiftMarkdownView/CompactHeadingStyle":{"url":"\/documentation\/swiftmarkdownview\/compactheadingstyle","abstract":[{"text":"A compact heading style with reduced typography scale.","type":"text"}],"identifier":"doc:\/\/SwiftMarkdownView\/documentation\/SwiftMarkdownView\/CompactHeadingStyle","title":"CompactHeadingStyle","role":"symbol","fragments":[{"kind":"keyword","text":"struct"},{"kind":"text","text":" "},{"kind":"identifier","text":"CompactHeadingStyle"}],"type":"topic","navigatorTitle":[{"kind":"identifier","text":"CompactHeadingStyle"}],"kind":"symbol"},"doc://SwiftMarkdownView/documentation/SwiftMarkdownView/MermaidDiagramView":{"role":"symbol","identifier":"doc:\/\/SwiftMarkdownView\/documentation\/SwiftMarkdownView\/MermaidDiagramView","title":"MermaidDiagramView","navigatorTitle":[{"text":"MermaidDiagramView","kind":"identifier"}],"abstract":[{"text":"A view that renders Mermaid diagrams using WebKit.","type":"text"}],"kind":"symbol","type":"topic","url":"\/documentation\/swiftmarkdownview\/mermaiddiagramview","fragments":[{"text":"struct","kind":"keyword"},{"text":" ","kind":"text"},{"text":"MermaidDiagramView","kind":"identifier"}]},"doc://SwiftMarkdownView/documentation/SwiftMarkdownView/TableCatalogView":{"type":"topic","kind":"symbol","fragments":[{"text":"struct","kind":"keyword"},{"text":" ","kind":"text"},{"text":"TableCatalogView","kind":"identifier"}],"identifier":"doc:\/\/SwiftMarkdownView\/documentation\/SwiftMarkdownView\/TableCatalogView","url":"\/documentation\/swiftmarkdownview\/tablecatalogview","title":"TableCatalogView","role":"symbol","navigatorTitle":[{"text":"TableCatalogView","kind":"identifier"}],"abstract":[{"type":"text","text":"Catalog view for table elements."}]},"doc://SwiftMarkdownView/documentation/SwiftMarkdownView/BundledMermaidScriptProvider":{"role":"symbol","identifier":"doc:\/\/SwiftMarkdownView\/documentation\/SwiftMarkdownView\/BundledMermaidScriptProvider","abstract":[{"text":"A Mermaid script provider that loads from the app bundle.","type":"text"}],"fragments":[{"text":"struct","kind":"keyword"},{"text":" ","kind":"text"},{"text":"BundledMermaidScriptProvider","kind":"identifier"}],"type":"topic","title":"BundledMermaidScriptProvider","kind":"symbol","url":"\/documentation\/swiftmarkdownview\/bundledmermaidscriptprovider","navigatorTitle":[{"text":"BundledMermaidScriptProvider","kind":"identifier"}]},"doc://SwiftMarkdownView/documentation/SwiftMarkdownView/CategoryItemRow":{"url":"\/documentation\/swiftmarkdownview\/categoryitemrow","title":"CategoryItemRow","identifier":"doc:\/\/SwiftMarkdownView\/documentation\/SwiftMarkdownView\/CategoryItemRow","abstract":[{"type":"text","text":"A row for displaying a catalog item in a list."}],"fragments":[{"kind":"keyword","text":"struct"},{"kind":"text","text":" "},{"kind":"identifier","text":"CategoryItemRow"}],"type":"topic","kind":"symbol","role":"symbol","navigatorTitle":[{"text":"CategoryItemRow","kind":"identifier"}]},"doc://SwiftMarkdownView/documentation/SwiftMarkdownView/AdaptiveMermaidView":{"identifier":"doc:\/\/SwiftMarkdownView\/documentation\/SwiftMarkdownView\/AdaptiveMermaidView","abstract":[{"type":"text","text":"An adaptive view that uses native WebView on iOS 26+ or falls back to code display."}],"title":"AdaptiveMermaidView","navigatorTitle":[{"text":"AdaptiveMermaidView","kind":"identifier"}],"fragments":[{"text":"struct","kind":"keyword"},{"text":" ","kind":"text"},{"text":"AdaptiveMermaidView","kind":"identifier"}],"role":"symbol","kind":"symbol","type":"topic","url":"\/documentation\/swiftmarkdownview\/adaptivemermaidview"},"doc://SwiftMarkdownView/documentation/SwiftMarkdownView/TaskListCatalogView":{"abstract":[{"text":"Catalog view for task list (checkbox) elements.","type":"text"}],"type":"topic","kind":"symbol","role":"symbol","fragments":[{"kind":"keyword","text":"struct"},{"kind":"text","text":" "},{"kind":"identifier","text":"TaskListCatalogView"}],"url":"\/documentation\/swiftmarkdownview\/tasklistcatalogview","identifier":"doc:\/\/SwiftMarkdownView\/documentation\/SwiftMarkdownView\/TaskListCatalogView","navigatorTitle":[{"kind":"identifier","text":"TaskListCatalogView"}],"title":"TaskListCatalogView"},"doc://SwiftMarkdownView/documentation/SwiftMarkdownView/TableRow":{"abstract":[{"text":"Represents a single row in a table.","type":"text"}],"url":"\/documentation\/swiftmarkdownview\/tablerow","navigatorTitle":[{"text":"TableRow","kind":"identifier"}],"type":"topic","role":"symbol","title":"TableRow","fragments":[{"text":"struct","kind":"keyword"},{"text":" ","kind":"text"},{"text":"TableRow","kind":"identifier"}],"identifier":"doc:\/\/SwiftMarkdownView\/documentation\/SwiftMarkdownView\/TableRow","kind":"symbol"},"doc://SwiftMarkdownView/documentation/SwiftMarkdownView/HighlightedCodeView":{"title":"HighlightedCodeView","kind":"symbol","url":"\/documentation\/swiftmarkdownview\/highlightedcodeview","abstract":[{"text":"A SwiftUI view that renders syntax-highlighted code asynchronously.","type":"text"}],"role":"symbol","navigatorTitle":[{"text":"HighlightedCodeView","kind":"identifier"}],"identifier":"doc:\/\/SwiftMarkdownView\/documentation\/SwiftMarkdownView\/HighlightedCodeView","type":"topic","fragments":[{"text":"struct","kind":"keyword"},{"text":" ","kind":"text"},{"text":"HighlightedCodeView","kind":"identifier"}]},"doc://SwiftMarkdownView/documentation/SwiftMarkdownView/MarkdownColors":{"kind":"symbol","type":"topic","url":"\/documentation\/swiftmarkdownview\/markdowncolors","navigatorTitle":[{"kind":"identifier","text":"MarkdownColors"}],"fragments":[{"kind":"keyword","text":"enum"},{"kind":"text","text":" "},{"kind":"identifier","text":"MarkdownColors"}],"role":"symbol","identifier":"doc:\/\/SwiftMarkdownView\/documentation\/SwiftMarkdownView\/MarkdownColors","title":"MarkdownColors","abstract":[{"text":"Color mappings for Markdown elements using DesignSystem ColorPalette.","type":"text"}]},"doc://SwiftMarkdownView/documentation/SwiftMarkdownView/CodeSnippetView":{"kind":"symbol","type":"topic","abstract":[{"text":"A view for displaying Swift code snippets with syntax highlighting.","type":"text"}],"fragments":[{"text":"struct","kind":"keyword"},{"text":" ","kind":"text"},{"text":"CodeSnippetView","kind":"identifier"}],"identifier":"doc:\/\/SwiftMarkdownView\/documentation\/SwiftMarkdownView\/CodeSnippetView","url":"\/documentation\/swiftmarkdownview\/codesnippetview","role":"symbol","navigatorTitle":[{"text":"CodeSnippetView","kind":"identifier"}],"title":"CodeSnippetView"},"doc://SwiftMarkdownView/documentation/SwiftMarkdownView/TableStyleCatalogView":{"identifier":"doc:\/\/SwiftMarkdownView\/documentation\/SwiftMarkdownView\/TableStyleCatalogView","navigatorTitle":[{"kind":"identifier","text":"TableStyleCatalogView"}],"type":"topic","abstract":[{"text":"Catalog view for TableStyle configuration.","type":"text"}],"fragments":[{"kind":"keyword","text":"struct"},{"kind":"text","text":" "},{"kind":"identifier","text":"TableStyleCatalogView"}],"title":"TableStyleCatalogView","kind":"symbol","url":"\/documentation\/swiftmarkdownview\/tablestylecatalogview","role":"symbol"},"doc://SwiftMarkdownView/documentation/SwiftMarkdownView/MinimalCodeBlockStyle":{"navigatorTitle":[{"text":"MinimalCodeBlockStyle","kind":"identifier"}],"identifier":"doc:\/\/SwiftMarkdownView\/documentation\/SwiftMarkdownView\/MinimalCodeBlockStyle","url":"\/documentation\/swiftmarkdownview\/minimalcodeblockstyle","abstract":[{"type":"text","text":"A minimal code block style without decorations."}],"kind":"symbol","role":"symbol","fragments":[{"text":"struct","kind":"keyword"},{"text":" ","kind":"text"},{"text":"MinimalCodeBlockStyle","kind":"identifier"}],"title":"MinimalCodeBlockStyle","type":"topic"},"doc://SwiftMarkdownView/documentation/SwiftMarkdownView/SyntaxHighlighting":{"abstract":[{"type":"text","text":"コードブロックのシンタックスハイライトをカスタマイズする方法を学びます。"}],"identifier":"doc:\/\/SwiftMarkdownView\/documentation\/SwiftMarkdownView\/SyntaxHighlighting","title":"シンタックスハイライト","kind":"article","role":"article","type":"topic","url":"\/documentation\/swiftmarkdownview\/syntaxhighlighting"},"doc://SwiftMarkdownView/documentation/SwiftMarkdownView/BorderlessTableStyle":{"identifier":"doc:\/\/SwiftMarkdownView\/documentation\/SwiftMarkdownView\/BorderlessTableStyle","type":"topic","role":"symbol","fragments":[{"text":"struct","kind":"keyword"},{"text":" ","kind":"text"},{"text":"BorderlessTableStyle","kind":"identifier"}],"abstract":[{"type":"text","text":"A minimal table style without borders."}],"url":"\/documentation\/swiftmarkdownview\/borderlesstablestyle","kind":"symbol","title":"BorderlessTableStyle","navigatorTitle":[{"text":"BorderlessTableStyle","kind":"identifier"}]},"doc://SwiftMarkdownView/documentation/SwiftMarkdownView/SubtleLinkStyle":{"kind":"symbol","title":"SubtleLinkStyle","url":"\/documentation\/swiftmarkdownview\/subtlelinkstyle","identifier":"doc:\/\/SwiftMarkdownView\/documentation\/SwiftMarkdownView\/SubtleLinkStyle","role":"symbol","navigatorTitle":[{"kind":"identifier","text":"SubtleLinkStyle"}],"type":"topic","abstract":[{"type":"text","text":"A subtle link style without underline."}],"fragments":[{"kind":"keyword","text":"struct"},{"kind":"text","text":" "},{"kind":"identifier","text":"SubtleLinkStyle"}]},"doc://SwiftMarkdownView/documentation/SwiftMarkdownView/MarkdownCatalogListView":{"type":"topic","kind":"symbol","navigatorTitle":[{"text":"MarkdownCatalogListView","kind":"identifier"}],"fragments":[{"text":"struct","kind":"keyword"},{"text":" ","kind":"text"},{"text":"MarkdownCatalogListView","kind":"identifier"}],"identifier":"doc:\/\/SwiftMarkdownView\/documentation\/SwiftMarkdownView\/MarkdownCatalogListView","role":"symbol","title":"MarkdownCatalogListView","abstract":[{"type":"text","text":"A list-based catalog view for compact layouts."}],"url":"\/documentation\/swiftmarkdownview\/markdowncataloglistview"},"doc://SwiftMarkdownView/documentation/SwiftMarkdownView/MarkdownCatalogSplitView":{"abstract":[{"type":"text","text":"A split-view catalog for regular layouts."}],"fragments":[{"text":"struct","kind":"keyword"},{"text":" ","kind":"text"},{"text":"MarkdownCatalogSplitView","kind":"identifier"}],"title":"MarkdownCatalogSplitView","navigatorTitle":[{"text":"MarkdownCatalogSplitView","kind":"identifier"}],"url":"\/documentation\/swiftmarkdownview\/markdowncatalogsplitview","role":"symbol","type":"topic","identifier":"doc:\/\/SwiftMarkdownView\/documentation\/SwiftMarkdownView\/MarkdownCatalogSplitView","kind":"symbol"},"doc://SwiftMarkdownView/documentation/SwiftMarkdownView/DefaultCodeBlockStyle":{"title":"DefaultCodeBlockStyle","abstract":[{"text":"The default code block style with sensible defaults.","type":"text"}],"type":"topic","role":"symbol","navigatorTitle":[{"kind":"identifier","text":"DefaultCodeBlockStyle"}],"identifier":"doc:\/\/SwiftMarkdownView\/documentation\/SwiftMarkdownView\/DefaultCodeBlockStyle","url":"\/documentation\/swiftmarkdownview\/defaultcodeblockstyle","kind":"symbol","fragments":[{"kind":"keyword","text":"struct"},{"kind":"text","text":" "},{"kind":"identifier","text":"DefaultCodeBlockStyle"}]},"doc://SwiftMarkdownView/documentation/SwiftMarkdownView/TerminalCodeBlockStyle":{"identifier":"doc:\/\/SwiftMarkdownView\/documentation\/SwiftMarkdownView\/TerminalCodeBlockStyle","role":"symbol","kind":"symbol","fragments":[{"text":"struct","kind":"keyword"},{"text":" ","kind":"text"},{"text":"TerminalCodeBlockStyle","kind":"identifier"}],"url":"\/documentation\/swiftmarkdownview\/terminalcodeblockstyle","type":"topic","title":"TerminalCodeBlockStyle","abstract":[{"type":"text","text":"A terminal-inspired code block style."}],"navigatorTitle":[{"text":"TerminalCodeBlockStyle","kind":"identifier"}]},"doc://SwiftMarkdownView/documentation/SwiftMarkdownView/InlineCodeCatalogView":{"abstract":[{"text":"Catalog view for inline code elements.","type":"text"}],"identifier":"doc:\/\/SwiftMarkdownView\/documentation\/SwiftMarkdownView\/InlineCodeCatalogView","type":"topic","role":"symbol","fragments":[{"text":"struct","kind":"keyword"},{"text":" ","kind":"text"},{"text":"InlineCodeCatalogView","kind":"identifier"}],"navigatorTitle":[{"text":"InlineCodeCatalogView","kind":"identifier"}],"title":"InlineCodeCatalogView","kind":"symbol","url":"\/documentation\/swiftmarkdownview\/inlinecodecatalogview"},"doc://SwiftMarkdownView/documentation/SwiftMarkdownView/LinkStyleCatalogView":{"type":"topic","title":"LinkStyleCatalogView","abstract":[{"text":"Catalog view for LinkStyle configuration.","type":"text"}],"identifier":"doc:\/\/SwiftMarkdownView\/documentation\/SwiftMarkdownView\/LinkStyleCatalogView","fragments":[{"text":"struct","kind":"keyword"},{"text":" ","kind":"text"},{"text":"LinkStyleCatalogView","kind":"identifier"}],"navigatorTitle":[{"text":"LinkStyleCatalogView","kind":"identifier"}],"url":"\/documentation\/swiftmarkdownview\/linkstylecatalogview","kind":"symbol","role":"symbol"},"doc://SwiftMarkdownView/documentation/SwiftMarkdownView/MarkdownCatalogView":{"kind":"symbol","navigatorTitle":[{"text":"MarkdownCatalogView","kind":"identifier"}],"role":"symbol","fragments":[{"text":"struct","kind":"keyword"},{"text":" ","kind":"text"},{"text":"MarkdownCatalogView","kind":"identifier"}],"abstract":[{"type":"text","text":"The main entry point for the Markdown catalog."}],"url":"\/documentation\/swiftmarkdownview\/markdowncatalogview","type":"topic","title":"MarkdownCatalogView","identifier":"doc:\/\/SwiftMarkdownView\/documentation\/SwiftMarkdownView\/MarkdownCatalogView"},"doc://SwiftMarkdownView/documentation/SwiftMarkdownView/MarkdownView":{"abstract":[{"type":"text","text":"A SwiftUI view that renders Markdown content."}],"navigatorTitle":[{"text":"MarkdownView","kind":"identifier"}],"identifier":"doc:\/\/SwiftMarkdownView\/documentation\/SwiftMarkdownView\/MarkdownView","title":"MarkdownView","url":"\/documentation\/swiftmarkdownview\/markdownview","type":"topic","role":"symbol","fragments":[{"text":"struct","kind":"keyword"},{"text":" ","kind":"text"},{"text":"MarkdownView","kind":"identifier"}],"kind":"symbol"},"doc://SwiftMarkdownView/documentation/SwiftMarkdownView/HeadingStyle":{"title":"HeadingStyle","identifier":"doc:\/\/SwiftMarkdownView\/documentation\/SwiftMarkdownView\/HeadingStyle","type":"topic","url":"\/documentation\/swiftmarkdownview\/headingstyle","navigatorTitle":[{"kind":"identifier","text":"HeadingStyle"}],"kind":"symbol","abstract":[{"type":"text","text":"A protocol that defines the visual styling for headings."}],"fragments":[{"kind":"keyword","text":"protocol"},{"kind":"text","text":" "},{"kind":"identifier","text":"HeadingStyle"}],"role":"symbol"},"doc://SwiftMarkdownView/documentation/SwiftMarkdownView/OrderedListCatalogView":{"abstract":[{"type":"text","text":"Catalog view for ordered (numbered) list elements."}],"title":"OrderedListCatalogView","navigatorTitle":[{"text":"OrderedListCatalogView","kind":"identifier"}],"type":"topic","fragments":[{"text":"struct","kind":"keyword"},{"text":" ","kind":"text"},{"text":"OrderedListCatalogView","kind":"identifier"}],"url":"\/documentation\/swiftmarkdownview\/orderedlistcatalogview","identifier":"doc:\/\/SwiftMarkdownView\/documentation\/SwiftMarkdownView\/OrderedListCatalogView","kind":"symbol","role":"symbol"},"doc://SwiftMarkdownView/documentation/SwiftMarkdownView/LinkStyle":{"url":"\/documentation\/swiftmarkdownview\/linkstyle","kind":"symbol","type":"topic","abstract":[{"type":"text","text":"A protocol that defines the visual styling for links."}],"role":"symbol","identifier":"doc:\/\/SwiftMarkdownView\/documentation\/SwiftMarkdownView\/LinkStyle","fragments":[{"text":"protocol","kind":"keyword"},{"text":" ","kind":"text"},{"text":"LinkStyle","kind":"identifier"}],"title":"LinkStyle","navigatorTitle":[{"text":"LinkStyle","kind":"identifier"}]},"doc://SwiftMarkdownView/documentation/SwiftMarkdownView/MonochromeLinkStyle":{"type":"topic","abstract":[{"type":"text","text":"A monochrome link style that blends with the text."}],"fragments":[{"kind":"keyword","text":"struct"},{"kind":"text","text":" "},{"kind":"identifier","text":"MonochromeLinkStyle"}],"kind":"symbol","title":"MonochromeLinkStyle","role":"symbol","navigatorTitle":[{"kind":"identifier","text":"MonochromeLinkStyle"}],"url":"\/documentation\/swiftmarkdownview\/monochromelinkstyle","identifier":"doc:\/\/SwiftMarkdownView\/documentation\/SwiftMarkdownView\/MonochromeLinkStyle"},"doc://SwiftMarkdownView/documentation/SwiftMarkdownView/MermaidDiagrams":{"role":"article","identifier":"doc:\/\/SwiftMarkdownView\/documentation\/SwiftMarkdownView\/MermaidDiagrams","url":"\/documentation\/swiftmarkdownview\/mermaiddiagrams","kind":"article","abstract":[{"type":"text","text":"Markdownコードブロック内でMermaidダイアグラムを表示する方法を学びます。"}],"type":"topic","title":"Mermaidダイアグラム"},"doc://SwiftMarkdownView/documentation/SwiftMarkdownView/SwiftUICore":{"identifier":"doc:\/\/SwiftMarkdownView\/documentation\/SwiftMarkdownView\/SwiftUICore","type":"topic","url":"\/documentation\/swiftmarkdownview\/swiftuicore","kind":"symbol","role":"collection","title":"SwiftUICore","abstract":[]},"doc://SwiftMarkdownView/documentation/SwiftMarkdownView/ImageCatalogView":{"fragments":[{"text":"struct","kind":"keyword"},{"text":" ","kind":"text"},{"text":"ImageCatalogView","kind":"identifier"}],"type":"topic","role":"symbol","url":"\/documentation\/swiftmarkdownview\/imagecatalogview","kind":"symbol","identifier":"doc:\/\/SwiftMarkdownView\/documentation\/SwiftMarkdownView\/ImageCatalogView","abstract":[{"text":"Catalog view for image elements.","type":"text"}],"title":"ImageCatalogView","navigatorTitle":[{"text":"ImageCatalogView","kind":"identifier"}]},"doc://SwiftMarkdownView/documentation/SwiftMarkdownView/GettingStarted":{"url":"\/documentation\/swiftmarkdownview\/gettingstarted","role":"article","abstract":[{"type":"text","text":"SwiftMarkdownViewを使ってMarkdownを表示する基本的な方法を学びます。"}],"title":"はじめに","kind":"article","type":"topic","identifier":"doc:\/\/SwiftMarkdownView\/documentation\/SwiftMarkdownView\/GettingStarted"}}}